tbshacl/__init__.py
tbshacl/__main__.py
tbshacl/report.py
pyTBSHACL-0.0.1.dist-info/LICENSE
pyTBSHACL-0.0.1.dist-info/METADATA
pyTBSHACL-0.0.1.dist-info/WHEEL
pyTBSHACL-0.0.1.dist-info/entry_points.txt
pyTBSHACL-0.0.1.dist-info/top_level.txt
pyTBSHACL-0.0.1.dist-info/RECORD
