Metadata-Version: 2.1
Name: pyTBSHACL
Version: 0.0.1
Summary: Python wrapper for TopBraid SHACL validator
Home-page: https://github.com/datadavev/pyTBSHACL
Author: Dave Vieglais
License: Apache 2.0
Keywords: SHACL RDF validation JSON-LD
Platform: UNKNOWN
Classifier: Development Status :: 5 - Production/Stable
Classifier: Intended Audience :: Developers
Classifier: Topic :: Scientific/Engineering
Classifier: License :: OSI Approved :: Apache Software License
Classifier: Programming Language :: Python :: 3
Classifier: Programming Language :: Python :: 3.5
Requires-Dist: rdflib (>=4.2)
Requires-Dist: jinja2
